m3u_helper/__init__.py
m3u_helper/__main__.py
m3u_helper/channel_group.py
m3u_helper/config.py
m3u_helper/connect_checker.py
m3u_helper/help.info
m3u_helper/main.py
m3u_helper_icexmoon-0.0.2.dist-info/LICENSE
m3u_helper_icexmoon-0.0.2.dist-info/METADATA
m3u_helper_icexmoon-0.0.2.dist-info/WHEEL
m3u_helper_icexmoon-0.0.2.dist-info/entry_points.txt
m3u_helper_icexmoon-0.0.2.dist-info/top_level.txt
m3u_helper_icexmoon-0.0.2.dist-info/RECORD
