Metadata-Version: 2.1
Name: m3u-helper-icexmoon
Version: 0.0.2
Summary: Format m3u file according to the Chinese custom.
Home-page: https://github.com/icexmoon/m3u-helper
Author: icexmoon
Author-email: icexmoon@qq.com
License: UNKNOWN
Project-URL: Bug Tracker, https://github.com/icexmoon/m3u-helper/issues
Platform: UNKNOWN
Classifier: Programming Language :: Python :: 3
Classifier: License :: OSI Approved :: MIT License
Classifier: Operating System :: OS Independent
Requires-Python: >=3.9
License-File: LICENSE
Requires-Dist: m3u8
Requires-Dist: tqdm
Requires-Dist: requests
